flask_postgresql_audit/__init__.py
flask_postgresql_audit/base.py
flask_postgresql_audit/core.py
flask_postgresql_audit/descriptors.py
flask_postgresql_audit/models.py
flask_postgresql_audit/typing.py
flask_postgresql_audit/utils.py
flask_postgresql_audit/alembic/__init__.py
flask_postgresql_audit/alembic/entities.py
flask_postgresql_audit/alembic/schema.py
flask_postgresql_audit/alembic/setup.py
flask_postgresql_audit/extensions/__init__.py
flask_postgresql_audit/extensions/alembic_utils/__init__.py
flask_postgresql_audit/extensions/alembic_utils/pg_aggregate.py
flask_postgresql_audit/extensions/document_staging/__init__.py
flask_postgresql_audit/extensions/document_staging/enum.py
flask_postgresql_audit/extensions/document_staging/listener.py
flask_postgresql_audit/extensions/document_staging/model.py
flask_postgresql_audit/templates/audit_trigger_delete.sql
flask_postgresql_audit/templates/audit_trigger_insert.sql
flask_postgresql_audit/templates/audit_trigger_update.sql
flask_postgresql_audit/templates/create_activity.sql
flask_postgresql_audit/templates/create_schema.sql
flask_postgresql_audit/templates/drop_schema.sql
flask_postgresql_audit/templates/get_pk_values.sql
flask_postgresql_audit/templates/get_setting.sql
flask_postgresql_audit/templates/jsonb_subtract.sql
flask_postgresql_audit/templates/row_audit_trigger.sql
flask_postgresql_audit/templates/row_create_activity.sql
flask_postgresql_audit-1.0.7.dist-info/METADATA
flask_postgresql_audit-1.0.7.dist-info/WHEEL
flask_postgresql_audit-1.0.7.dist-info/licenses/LICENSE
flask_postgresql_audit-1.0.7.dist-info/RECORD
