Metadata-Version: 2.4
Name: flask-postgresql_audit
Version: 1.0.7
Summary: Versioning and auditing extension for PostgreSQL and SQLAlchemy.
Project-URL: Homepage, https://github.com/higamigu/flask-postgresql-audit
Author-email: Higamigu <higamigu@gmail.com>, Konsta Vesterinen <konsta@fastmonkeys.com>
License-Expression: BSD-2-Clause
License-File: LICENSE
Classifier: Environment :: Web Environment
Classifier: Intended Audience :: Developers
Classifier: License :: OSI Approved :: BSD License
Classifier: Operating System :: OS Independent
Classifier: Programming Language :: Python
Classifier: Programming Language :: Python :: 3
Classifier: Programming Language :: Python :: 3.11
Classifier: Programming Language :: Python :: 3.12
Classifier: Programming Language :: Python :: 3.13
Classifier: Topic :: Internet :: WWW/HTTP :: Dynamic Content
Classifier: Topic :: Software Development :: Libraries :: Python Modules
Requires-Python: >=3.11
Requires-Dist: alembic-utils>=0.8.8
Requires-Dist: alembic>=1.17.0
Requires-Dist: flask-sqlalchemy>=3.1.1
Requires-Dist: flask>=3.1.2
Requires-Dist: psycopg2>=2.9.11
